pyscan/__init__.py
pyscan/main.py
pyscan/service_names.py
pyscan_tool-0.1.1.dist-info/LICENSE.md
pyscan_tool-0.1.1.dist-info/METADATA
pyscan_tool-0.1.1.dist-info/WHEEL
pyscan_tool-0.1.1.dist-info/entry_points.txt
pyscan_tool-0.1.1.dist-info/top_level.txt
pyscan_tool-0.1.1.dist-info/RECORD
